fne/__init__.py
fne/fne_torch.py
fne-1.6.5.dist-info/LICENSE
fne-1.6.5.dist-info/METADATA
fne-1.6.5.dist-info/WHEEL
fne-1.6.5.dist-info/top_level.txt
fne-1.6.5.dist-info/RECORD
