Metadata-Version: 2.1
Name: fne
Version: 1.6.5
Summary: Full Network Embedding implementation in pytorch.
Author-email: Adrian Tormos <adrian.tormos@bsc.es>
Project-URL: repository, https://github.com/HPAI-BSC/fne
Keywords: CNN,transfer learning,embedding
Classifier: License :: OSI Approved :: GNU General Public License v3 or later (GPLv3+)
Classifier: Programming Language :: Python
Classifier: Programming Language :: Python :: 3
Requires-Python: >=3.8
License-File: LICENSE
Requires-Dist: torch (>=1.12.1)
Requires-Dist: torchvision (>=0.13.1)
Requires-Dist: typing-extensions (>=4.1.1)
Requires-Dist: scikit-learn (>=0.24.2)
Provides-Extra: dev
Requires-Dist: pytest ; extra == 'dev'
